{
    "locales": [{
        "smartling": "en-US",
        "application": "en"
    }, {
        "smartling": "af",
        "application": "aa"
    }, {
        "smartling": "ar",
        "application": "ar"
    }, {
        "smartling": "bg-BG",
        "application": "bg"
    }, {
        "smartling": "bn-BD",
        "application": "bn"
    }, {
        "smartling": "ca-ES",
        "application": "ca"
    }, {
        "smartling": "cs-CZ",
        "application": "cs"
    }, {
        "smartling": "da-DK",
        "application": "da"
    }, {
        "smartling": "de",
        "application": "de"
    }, {
        "smartling": "el",
        "application": "el"
    }, {
        "smartling": "en-AU",
        "application": "en-rAU"
    }, {
        "smartling": "en-GB",
        "application": "en-rGB"
    }, {
        "smartling": "es-AR",
        "application": "es-rAR"
    }, {
        "smartling": "es-LA",
        "application": "es"
    }, {
        "smartling": "es-ES",
        "application": "es-rES"
    }, {
        "smartling": "es-MX",
        "application": "es-rMX"
    }, {
        "smartling": "fi-FI",
        "application": "fi"
    }, {
        "smartling": "fr-CA",
        "application": "fr-rCA"
    }, {
        "smartling": "fr-FR",
        "application": "fr"
    }, {
        "smartling": "he-IL",
        "application": "he"
    }, {
        "smartling": "hi-IN",
        "application": "hi"
    }, {
        "smartling": "hu-HU",
        "application": "hu"
    }, {
        "smartling": "id-ID",
        "application": "in"
    }, {
        "smartling": "it",
        "application": "it"
    }, {
        "smartling": "he-IL",
        "application": "iw"
    }, {
        "smartling": "ja",
        "application": "ja"
    }, {
        "smartling": "ko",
        "application": "ko"
    }, {
        "smartling": "lt-LT",
        "application": "lt"
    }, {
        "smartling": "lv-LV",
        "application": "lv"
    }, {
        "smartling": "ms",
        "application": "ms"
    }, {
        "smartling": "nb-NO",
        "application": "nb"
    }, {
        "smartling": "nl",
        "application": "nl"
    }, {
        "smartling": "nb-NO",
        "application": "no"
    }, {
        "smartling": "pl",
        "application": "pl"
    }, {
        "smartling": "pt-BR",
        "application": "pt"
    }, {
        "smartling": "pt-BR",
        "application": "pt-rBR"
    }, {
        "smartling": "pt-PT",
        "application": "pt-rPT"
    }, {
        "smartling": "ro-RO",
        "application": "ro"
    }, {
        "smartling": "ru",
        "application": "ru"
    }, {
        "smartling": "sk-SK",
        "application": "sk"
    }, {
        "smartling": "sl-SI",
        "application": "sl"
    }, {
        "smartling": "sr-RS",
        "application": "sr"
    }, {
        "smartling": "sv-SE",
        "application": "sv"
    }, {
        "smartling": "ta-IN",
        "application": "ta"
    }, {
        "smartling": "te-IN",
        "application": "te"
    }, {
        "smartling": "th",
        "application": "th"
    }, {
        "smartling": "tl-PH",
        "application": "tl"
    }, {
        "smartling": "tr",
        "application": "tr"
    }, {
        "smartling": "uk-UA",
        "application": "uk"
    }, {
        "smartling": "vi-VN",
        "application": "vi"
    }, {
        "smartling": "zh-CN",
        "application": "zh-rCN"
    }, {
        "smartling": "zh-TW",
        "application": "zh-rTW"
    }],
    "resourceSets": [{
        "type": "android",
        "pathRegex": "values-[a-zA-Z]\\/strings\\.xml",
        "translationPathExpression": "values-${locale}/${originalFile.baseName}.${originalFile.extension}",
        "translationCommitMessage": "Translate ${originalFile.fullName} to ${locale}"
    }]
}
